Workbook
Name aporte_mensal: Ferramenta!$D$12:$D$12
Name dividendos_mensal: Ferramenta!$D$16:$D$16
Name patrimonio_total: Ferramenta!$D$15:$D$15
Name periodo_aporte: Ferramenta!$D$13:$D$13
Name rendimento_carteira: Ferramenta!$D$6
Name salario_carteira: Ferramenta!$D$5:$D$5
Name sugestao_carteira: Ferramenta!$D$8:$D$8
Name taxa_mensal: Ferramenta!$D$14:$D$14

Sheet Ferramenta
B4: CONFIGURAÇÕES DA CARTEIRA ⚙️
B5: Salário atual do investidor | D5: 15000
B6: Rendimento da minha carteira | D6: 0.009
B7: Perfil do Investidor | D7: CONSERVADOR
B8: Sugestão de Investimento Fixa Baseada no Salário (30%) | D8: =D5*30% -> 4500
B11: INVESTIMENTO MENSAL 💸
B12: Quanto quero investir mensalmente? | D12: =C35 -> 4500
B13: Por quanto tempo? | D13: 5
B14: Qual a taxas de rendimento mensal? | D14: 0.01093
B15: Patrimônio total no período? | D15: =FV(D14,D13*12,D12*-1) -> 378708.23
B16: Qual o rendimento de dividendos mensal? | D16: =D15*$D$6 -> 3408.374
B19: CENÁRIOS SIMULADOS 📝 | D19: DIVIDENDOS
B20: ="Quanto terei em "&A22&IF(A22=1," ano"," anos")&" ?" -> Quanto terei em 1 ano ? | C20: =FV($D$14,A22*12,$D$12*-1) -> 57367.44 | D20: =C20*$D$6 -> 516.30696
B21: ="Quanto terei em "&A23&IF(A23=1," ano"," anos")&" ?" -> Quanto terei em 5 anos ? | C21: =FV($D$14,A23*12,$D$12*-1) -> 378708.23 | D21: =C21*$D$6 -> 3408.374
A22: 1 | B22: ="Quanto terei em "&A24&IF(A24=1," ano"," anos")&" ?" -> Quanto terei em 10 anos ? | C22: =FV($D$14,A24*12,$D$12*-1) -> 1105767.5 | D22: =C22*$D$6 -> 9951.9076
A23: 5 | B23: ="Quanto terei em "&A25&IF(A25=1," ano"," anos")&" ?" -> Quanto terei em 15 anos ? | C23: =FV($D$14,A25*12,$D$12*-1) -> 2501605.1 | D23: =C23*$D$6 -> 22514.446
A24: 10 | B24: ="Quanto terei em "&A26&IF(A26=1," ano"," anos")&" ?" -> Quanto terei em 20 anos ? | C24: =FV($D$14,A26*12,$D$12*-1) -> 5181390.4 | D24: =C24*$D$6 -> 46632.513
A25: 15 | B25: ="Quanto terei em "&A27&IF(A27=1," ano"," anos")&" ?" -> Quanto terei em 25 anos ? | C25: =FV($D$14,A27*12,$D$12*-1) -> 10326150 | D25: =C25*$D$6 -> 92935.348
A26: 20 | B26: ="Quanto terei em "&A28&IF(A28=1," ano"," anos")&" ?" -> Quanto terei em 30 anos ? | C26: =FV($D$14,A28*12,$D$12*-1) -> 20203266 | D26: =C26*$D$6 -> 181829.39
A27: 25 | B27: ="Quanto terei em "&A29&IF(A29=1," ano"," anos")&" ?" -> Quanto terei em 35 anos ? | C27: =FV($D$14,A29*12,$D$12*-1) -> 39165750 | D27: =C27*$D$6 -> 352491.75
A28: 30 | B28: ="Quanto terei em "&A30&IF(A30=1," ano"," anos")&" ?" -> Quanto terei em 40 anos ? | C28: =FV($D$14,A30*12,$D$12*-1) -> 75570690 | D28: =C28*$D$6 -> 680136.21
A29: 35 | B29: ="Quanto terei em "&A31&IF(A31=1," ano"," anos")&" ?" -> Quanto terei em 45 anos ? | C29: =FV($D$14,A31*12,$D$12*-1) -> 1.4546236e+08 | D29: =C29*$D$6 -> 1309161.2
A30: 40 | B30: ="Quanto terei em "&A32&IF(A32=1," ano"," anos")&" ?" -> Quanto terei em 50 anos ? | C30: =FV($D$14,A32*12,$D$12*-1) -> 2.7964319e+08 | D30: =C30*$D$6 -> 2516788.7
A31: 45
A32: 50
B33: SIMULAÇÃO DE DISTRIBUIÇÃO DE CARTEIRA CONFORME O *PERFIL* DO INVESTIDOR
B34: Perfil do Investidor | C34: =D7 -> CONSERVADOR | D34: SALÁRIO DO INVESTIDOR
B35: APORTE MENSAL SUGERIDO CONFORME PERFIL | C35: =IFERROR(D35*VLOOKUP(C34,Apoio!$I$4:$J$6,2,FALSE),0) -> 4500 | D35: =D5 -> 15000
B36: TIPOS DE FUNDOS DE INVESTIMENTO | C36: PERCENTUAL SUGERIDO | D36: VALORES
B37: TIJOLO | C37: =VLOOKUP($C$34&"-"&B37,Apoio!$A:$D,3,FALSE) -> 0.1 | D37: =$C$35*C37 -> 450
B38: PAPEL | C38: =VLOOKUP($C$34&"-"&B38,Apoio!$A:$D,3,FALSE) -> 0.5 | D38: =$C$35*C38 -> 2250
B39: FOF'S | C39: =VLOOKUP($C$34&"-"&B39,Apoio!$A:$D,3,FALSE) -> 0.05 | D39: =$C$35*C39 -> 225
B40: HÍBRIDOS | C40: =VLOOKUP($C$34&"-"&B40,Apoio!$A:$D,3,FALSE) -> 0.05 | D40: =$C$35*C40 -> 225
B41: RENDA FIXA | C41: =VLOOKUP($C$34&"-"&B41,Apoio!$A:$D,3,FALSE) -> 0.3 | D41: =$C$35*C41 -> 1350
B42: DESENVOLVIMENTO | C42: =VLOOKUP($C$34&"-"&B42,Apoio!$A:$D,3,FALSE) -> 0 | D42: =$C$35*C42 -> 0
B44: DISTRIBUIÇÃO DA CARTEIRA POR INVESTIMENTO 📊

Sheet Apoio
A1: Não altere os nomes dos perfis em C3, C12 e C21: eles formam as chaves usadas na busca da aba Ferramenta. Os percentuais de aporte de cada perfil ficam na tabela I3:J6.
A3: KEY | B3: Perfil do Investidor | C3: AGRESSIVO | D3: SALÁRIO DO INVESTIDOR | I3: PERFIL | J3: % DO SALÁRIO NO APORTE
B4: APORTE MENSAL | C4: =D4*VLOOKUP(C3,$I$4:$J$6,2,FALSE) -> 7500 | D4: =Ferramenta!D35 -> 15000 | G4: % | I4: AGRESSIVO | J4: 0.5
B5: TIPO DE FII | C5: PERCENTUAL | F5: AGRESSIVO-TIJOLO | G5: =VLOOKUP(F5,$A:$D,3,FALSE) -> 0.5 | I5: MODERADO | J5: 0.4
A6: =$C$3&"-"&B6 -> AGRESSIVO-TIJOLO | B6: TIJOLO | C6: 0.5 | D6: =$C$4*C6 -> 3750 | I6: CONSERVADOR | J6: 0.3
A7: =$C$3&"-"&B7 -> AGRESSIVO-PAPEL | B7: PAPEL | C7: 0.3 | D7: =$C$4*C7 -> 2250
A8: =$C$3&"-"&B8 -> AGRESSIVO-FOF'S | B8: FOF'S | C8: 0.1 | D8: =$C$4*C8 -> 750
A9: =$C$3&"-"&B9 -> AGRESSIVO-HÍBRIDOS | B9: HÍBRIDOS | C9: 0.1 | D9: =$C$4*C9 -> 750
A10: =$C$3&"-"&B10 -> AGRESSIVO-RENDA FIXA | B10: RENDA FIXA | C10: 0 | D10: =$C$4*C10 -> 0
A11: =$C$3&"-"&B11 -> AGRESSIVO-DESENVOLVIMENTO | B11: DESENVOLVIMENTO | C11: 0 | D11: =$C$4*C11 -> 0
B12: Perfil do Investidor | C12: MODERADO | D12: SALÁRIO DO INVESTIDOR
B13: APORTE MENSAL | C13: =D13*VLOOKUP(C12,$I$4:$J$6,2,FALSE) -> 6000 | D13: =Ferramenta!D35 -> 15000
B14: TIPO DE FII | C14: PERCENTUAL
A15: =$C$12&"-"&B15 -> MODERADO-TIJOLO | B15: TIJOLO | C15: 0.4 | D15: =$C$13*C15 -> 2400
A16: =$C$12&"-"&B16 -> MODERADO-PAPEL | B16: PAPEL | C16: 0.2 | D16: =$C$13*C16 -> 1200
A17: =$C$12&"-"&B17 -> MODERADO-FOF'S | B17: FOF'S | C17: 0.1 | D17: =$C$13*C17 -> 600
A18: =$C$12&"-"&B18 -> MODERADO-HÍBRIDOS | B18: HÍBRIDOS | C18: 0.1 | D18: =$C$13*C18 -> 600
A19: =$C$12&"-"&B19 -> MODERADO-RENDA FIXA | B19: RENDA FIXA | C19: 0.2 | D19: =$C$13*C19 -> 1200
A20: =$C$12&"-"&B20 -> MODERADO-DESENVOLVIMENTO | B20: DESENVOLVIMENTO | C20: 0 | D20: =$C$13*C20 -> 0
B21: Perfil do Investidor | C21: CONSERVADOR | D21: SALÁRIO DO INVESTIDOR
B22: APORTE MENSAL | C22: =D22*VLOOKUP(C21,$I$4:$J$6,2,FALSE) -> 4500 | D22: =Ferramenta!D35 -> 15000
B23: TIPO DE FII | C23: PERCENTUAL
A24: =$C$21&"-"&B24 -> CONSERVADOR-TIJOLO | B24: TIJOLO | C24: 0.1 | D24: =$C$22*C24 -> 450
A25: =$C$21&"-"&B25 -> CONSERVADOR-PAPEL | B25: PAPEL | C25: 0.5 | D25: =$C$22*C25 -> 2250
A26: =$C$21&"-"&B26 -> CONSERVADOR-FOF'S | B26: FOF'S | C26: 0.05 | D26: =$C$22*C26 -> 225
A27: =$C$21&"-"&B27 -> CONSERVADOR-HÍBRIDOS | B27: HÍBRIDOS | C27: 0.05 | D27: =$C$22*C27 -> 225
A28: =$C$21&"-"&B28 -> CONSERVADOR-RENDA FIXA | B28: RENDA FIXA | C28: 0.3 | D28: =$C$22*C28 -> 1350
A29: =$C$21&"-"&B29 -> CONSERVADOR-DESENVOLVIMENTO | B29: DESENVOLVIMENTO | C29: 0 | D29: =$C$22*C29 -> 0
